money/__init__.py
money/currency.py
money/exceptions.py
money/money.py
real_money-0.1.0.dist-info/LICENSE
real_money-0.1.0.dist-info/METADATA
real_money-0.1.0.dist-info/WHEEL
real_money-0.1.0.dist-info/top_level.txt
real_money-0.1.0.dist-info/RECORD
