Metadata-Version: 2.1
Name: real-money
Version: 0.1.0
Summary: Money module for python
License: MIT
Project-URL: Homepage, https://github.com/Sighery/real-money
Keywords: money currency
Classifier: Development Status :: 4 - Beta
Classifier: Intended Audience :: Developers
Classifier: License :: OSI Approved :: MIT License
Classifier: Programming Language :: Python :: 3
Requires-Python: >=3.7
License-File: LICENSE
Provides-Extra: babel
Requires-Dist: Babel <3.0,>=2.4.0 ; extra == 'babel'
Provides-Extra: dev
Requires-Dist: black ; extra == 'dev'
Requires-Dist: isort ; extra == 'dev'
Requires-Dist: pytest ; extra == 'dev'
Requires-Dist: real-money[babel] ; extra == 'dev'
